<root>
<class chordsig="java.util.concurrent.locks.ReentrantLock" line="2">
	<type  start="76" length="31" line="3" chordsig="java.util.concurrent.locks.Lock"/>
	<type  start="109" length="20" line="3" chordsig="java.io.Serializable"/>
<method
 chordsig="&lt;init&gt;:()V@java.util.concurrent.locks.ReentrantLock"
 sig="ReentrantLock()"
 line="5"
 startpos="140"
 endpos="153"
>
	<newexpr line="5" chordsig="&lt;init&gt;:(Ljava/lang/String;)V@java.lang.RuntimeException" start="168" length="16" type="invoke">
			<expr><![CDATA[new RuntimeException("Stub!")]]></expr>
		<param  start="164" length="29" line="5">
			<expr><![CDATA[new RuntimeException("Stub!")]]></expr>
		</param>
		<param  start="185" length="7" line="5">
			<expr><![CDATA["Stub!"]]></expr>
		</param>
	</newexpr>
	<type  start="168" length="16" line="5" chordsig="java.lang.RuntimeException"/>
</method>
<method
 chordsig="&lt;init&gt;:(Z)V@java.util.concurrent.locks.ReentrantLock"
 sig="ReentrantLock(boolean)"
 line="6"
 startpos="205"
 endpos="218"
>
	<marker line="-1" type="param">
		<operand  start="227" length="4" line="6">
			<expr><![CDATA[fair]]></expr>
		</operand>
	</marker>
	<newexpr line="6" chordsig="&lt;init&gt;:(Ljava/lang/String;)V@java.lang.RuntimeException" start="245" length="16" type="invoke">
			<expr><![CDATA[new RuntimeException("Stub!")]]></expr>
		<param  start="241" length="29" line="6">
			<expr><![CDATA[new RuntimeException("Stub!")]]></expr>
		</param>
		<param  start="262" length="7" line="6">
			<expr><![CDATA["Stub!"]]></expr>
		</param>
	</newexpr>
	<type  start="245" length="16" line="6" chordsig="java.lang.RuntimeException"/>
</method>
<method
 chordsig="lock:()V@java.util.concurrent.locks.ReentrantLock"
 sig="void lock()"
 line="7"
 startpos="287"
 endpos="291"
>
	<newexpr line="7" chordsig="&lt;init&gt;:(Ljava/lang/String;)V@java.lang.RuntimeException" start="306" length="16" type="invoke">
			<expr><![CDATA[new RuntimeException("Stub!")]]></expr>
		<param  start="302" length="29" line="7">
			<expr><![CDATA[new RuntimeException("Stub!")]]></expr>
		</param>
		<param  start="323" length="7" line="7">
			<expr><![CDATA["Stub!"]]></expr>
		</param>
	</newexpr>
	<type  start="306" length="16" line="7" chordsig="java.lang.RuntimeException"/>
</method>
<method
 chordsig="lockInterruptibly:()V@java.util.concurrent.locks.ReentrantLock"
 sig="void lockInterruptibly()"
 line="8"
 startpos="348"
 endpos="365"
>
	<newexpr line="8" chordsig="&lt;init&gt;:(Ljava/lang/String;)V@java.lang.RuntimeException" start="418" length="16" type="invoke">
			<expr><![CDATA[new RuntimeException("Stub!")]]></expr>
		<param  start="414" length="29" line="8">
			<expr><![CDATA[new RuntimeException("Stub!")]]></expr>
		</param>
		<param  start="435" length="7" line="8">
			<expr><![CDATA["Stub!"]]></expr>
		</param>
	</newexpr>
	<type  start="418" length="16" line="8" chordsig="java.lang.RuntimeException"/>
</method>
<method
 chordsig="tryLock:()Z@java.util.concurrent.locks.ReentrantLock"
 sig="boolean tryLock()"
 line="9"
 startpos="463"
 endpos="470"
>
	<newexpr line="9" chordsig="&lt;init&gt;:(Ljava/lang/String;)V@java.lang.RuntimeException" start="485" length="16" type="invoke">
			<expr><![CDATA[new RuntimeException("Stub!")]]></expr>
		<param  start="481" length="29" line="9">
			<expr><![CDATA[new RuntimeException("Stub!")]]></expr>
		</param>
		<param  start="502" length="7" line="9">
			<expr><![CDATA["Stub!"]]></expr>
		</param>
	</newexpr>
	<type  start="485" length="16" line="9" chordsig="java.lang.RuntimeException"/>
</method>
<method
 chordsig="tryLock:(JLjava/util/concurrent/TimeUnit;)Z@java.util.concurrent.locks.ReentrantLock"
 sig="boolean tryLock(long,TimeUnit)"
 line="10"
 startpos="530"
 endpos="537"
>
	<marker line="-1" type="param">
		<operand  start="543" length="7" line="10">
			<expr><![CDATA[timeout]]></expr>
		</operand>
	</marker>
	<marker line="-1" type="param">
		<operand  start="582" length="4" line="10">
			<expr><![CDATA[unit]]></expr>
		</operand>
	</marker>
	<type  start="552" length="29" line="10" chordsig="java.util.concurrent.TimeUnit"/>
	<newexpr line="10" chordsig="&lt;init&gt;:(Ljava/lang/String;)V@java.lang.RuntimeException" start="638" length="16" type="invoke">
			<expr><![CDATA[new RuntimeException("Stub!")]]></expr>
		<param  start="634" length="29" line="10">
			<expr><![CDATA[new RuntimeException("Stub!")]]></expr>
		</param>
		<param  start="655" length="7" line="10">
			<expr><![CDATA["Stub!"]]></expr>
		</param>
	</newexpr>
	<type  start="638" length="16" line="10" chordsig="java.lang.RuntimeException"/>
</method>
<method
 chordsig="unlock:()V@java.util.concurrent.locks.ReentrantLock"
 sig="void unlock()"
 line="11"
 startpos="680"
 endpos="686"
>
	<newexpr line="11" chordsig="&lt;init&gt;:(Ljava/lang/String;)V@java.lang.RuntimeException" start="701" length="16" type="invoke">
			<expr><![CDATA[new RuntimeException("Stub!")]]></expr>
		<param  start="697" length="29" line="11">
			<expr><![CDATA[new RuntimeException("Stub!")]]></expr>
		</param>
		<param  start="718" length="7" line="11">
			<expr><![CDATA["Stub!"]]></expr>
		</param>
	</newexpr>
	<type  start="701" length="16" line="11" chordsig="java.lang.RuntimeException"/>
</method>
<method
 chordsig="newCondition:()Ljava/util/concurrent/locks/Condition;@java.util.concurrent.locks.ReentrantLock"
 sig="Condition newCondition()"
 line="12"
 startpos="775"
 endpos="787"
>
	<type  start="738" length="36" line="12" chordsig="java.util.concurrent.locks.Condition"/>
	<newexpr line="12" chordsig="&lt;init&gt;:(Ljava/lang/String;)V@java.lang.RuntimeException" start="802" length="16" type="invoke">
			<expr><![CDATA[new RuntimeException("Stub!")]]></expr>
		<param  start="798" length="29" line="12">
			<expr><![CDATA[new RuntimeException("Stub!")]]></expr>
		</param>
		<param  start="819" length="7" line="12">
			<expr><![CDATA["Stub!"]]></expr>
		</param>
	</newexpr>
	<type  start="802" length="16" line="12" chordsig="java.lang.RuntimeException"/>
</method>
<method
 chordsig="getHoldCount:()I@java.util.concurrent.locks.ReentrantLock"
 sig="int getHoldCount()"
 line="13"
 startpos="843"
 endpos="855"
>
	<newexpr line="13" chordsig="&lt;init&gt;:(Ljava/lang/String;)V@java.lang.RuntimeException" start="870" length="16" type="invoke">
			<expr><![CDATA[new RuntimeException("Stub!")]]></expr>
		<param  start="866" length="29" line="13">
			<expr><![CDATA[new RuntimeException("Stub!")]]></expr>
		</param>
		<param  start="887" length="7" line="13">
			<expr><![CDATA["Stub!"]]></expr>
		</param>
	</newexpr>
	<type  start="870" length="16" line="13" chordsig="java.lang.RuntimeException"/>
</method>
<method
 chordsig="isHeldByCurrentThread:()Z@java.util.concurrent.locks.ReentrantLock"
 sig="boolean isHeldByCurrentThread()"
 line="14"
 startpos="915"
 endpos="936"
>
	<newexpr line="14" chordsig="&lt;init&gt;:(Ljava/lang/String;)V@java.lang.RuntimeException" start="951" length="16" type="invoke">
			<expr><![CDATA[new RuntimeException("Stub!")]]></expr>
		<param  start="947" length="29" line="14">
			<expr><![CDATA[new RuntimeException("Stub!")]]></expr>
		</param>
		<param  start="968" length="7" line="14">
			<expr><![CDATA["Stub!"]]></expr>
		</param>
	</newexpr>
	<type  start="951" length="16" line="14" chordsig="java.lang.RuntimeException"/>
</method>
<method
 chordsig="isLocked:()Z@java.util.concurrent.locks.ReentrantLock"
 sig="boolean isLocked()"
 line="15"
 startpos="996"
 endpos="1004"
>
	<newexpr line="15" chordsig="&lt;init&gt;:(Ljava/lang/String;)V@java.lang.RuntimeException" start="1019" length="16" type="invoke">
			<expr><![CDATA[new RuntimeException("Stub!")]]></expr>
		<param  start="1015" length="29" line="15">
			<expr><![CDATA[new RuntimeException("Stub!")]]></expr>
		</param>
		<param  start="1036" length="7" line="15">
			<expr><![CDATA["Stub!"]]></expr>
		</param>
	</newexpr>
	<type  start="1019" length="16" line="15" chordsig="java.lang.RuntimeException"/>
</method>
<method
 chordsig="isFair:()Z@java.util.concurrent.locks.ReentrantLock"
 sig="boolean isFair()"
 line="16"
 startpos="1070"
 endpos="1076"
>
	<newexpr line="16" chordsig="&lt;init&gt;:(Ljava/lang/String;)V@java.lang.RuntimeException" start="1091" length="16" type="invoke">
			<expr><![CDATA[new RuntimeException("Stub!")]]></expr>
		<param  start="1087" length="29" line="16">
			<expr><![CDATA[new RuntimeException("Stub!")]]></expr>
		</param>
		<param  start="1108" length="7" line="16">
			<expr><![CDATA["Stub!"]]></expr>
		</param>
	</newexpr>
	<type  start="1091" length="16" line="16" chordsig="java.lang.RuntimeException"/>
</method>
<method
 chordsig="getOwner:()Ljava/lang/Thread;@java.util.concurrent.locks.ReentrantLock"
 sig="Thread getOwner()"
 line="17"
 startpos="1148"
 endpos="1156"
>
	<type  start="1131" length="16" line="17" chordsig="java.lang.Thread"/>
	<newexpr line="17" chordsig="&lt;init&gt;:(Ljava/lang/String;)V@java.lang.RuntimeException" start="1171" length="16" type="invoke">
			<expr><![CDATA[new RuntimeException("Stub!")]]></expr>
		<param  start="1167" length="29" line="17">
			<expr><![CDATA[new RuntimeException("Stub!")]]></expr>
		</param>
		<param  start="1188" length="7" line="17">
			<expr><![CDATA["Stub!"]]></expr>
		</param>
	</newexpr>
	<type  start="1171" length="16" line="17" chordsig="java.lang.RuntimeException"/>
</method>
<method
 chordsig="hasQueuedThreads:()Z@java.util.concurrent.locks.ReentrantLock"
 sig="boolean hasQueuedThreads()"
 line="18"
 startpos="1222"
 endpos="1238"
>
	<newexpr line="18" chordsig="&lt;init&gt;:(Ljava/lang/String;)V@java.lang.RuntimeException" start="1253" length="16" type="invoke">
			<expr><![CDATA[new RuntimeException("Stub!")]]></expr>
		<param  start="1249" length="29" line="18">
			<expr><![CDATA[new RuntimeException("Stub!")]]></expr>
		</param>
		<param  start="1270" length="7" line="18">
			<expr><![CDATA["Stub!"]]></expr>
		</param>
	</newexpr>
	<type  start="1253" length="16" line="18" chordsig="java.lang.RuntimeException"/>
</method>
<method
 chordsig="hasQueuedThread:(Ljava/lang/Thread;)Z@java.util.concurrent.locks.ReentrantLock"
 sig="boolean hasQueuedThread(Thread)"
 line="19"
 startpos="1304"
 endpos="1319"
>
	<marker line="-1" type="param">
		<operand  start="1337" length="6" line="19">
			<expr><![CDATA[thread]]></expr>
		</operand>
	</marker>
	<type  start="1320" length="16" line="19" chordsig="java.lang.Thread"/>
	<newexpr line="19" chordsig="&lt;init&gt;:(Ljava/lang/String;)V@java.lang.RuntimeException" start="1357" length="16" type="invoke">
			<expr><![CDATA[new RuntimeException("Stub!")]]></expr>
		<param  start="1353" length="29" line="19">
			<expr><![CDATA[new RuntimeException("Stub!")]]></expr>
		</param>
		<param  start="1374" length="7" line="19">
			<expr><![CDATA["Stub!"]]></expr>
		</param>
	</newexpr>
	<type  start="1357" length="16" line="19" chordsig="java.lang.RuntimeException"/>
</method>
<method
 chordsig="getQueueLength:()I@java.util.concurrent.locks.ReentrantLock"
 sig="int getQueueLength()"
 line="20"
 startpos="1404"
 endpos="1418"
>
	<newexpr line="20" chordsig="&lt;init&gt;:(Ljava/lang/String;)V@java.lang.RuntimeException" start="1433" length="16" type="invoke">
			<expr><![CDATA[new RuntimeException("Stub!")]]></expr>
		<param  start="1429" length="29" line="20">
			<expr><![CDATA[new RuntimeException("Stub!")]]></expr>
		</param>
		<param  start="1450" length="7" line="20">
			<expr><![CDATA["Stub!"]]></expr>
		</param>
	</newexpr>
	<type  start="1433" length="16" line="20" chordsig="java.lang.RuntimeException"/>
</method>
<method
 chordsig="getQueuedThreads:()Ljava/util/Collection;@java.util.concurrent.locks.ReentrantLock"
 sig="Collection&lt;Thread&gt; getQueuedThreads()"
 line="21"
 startpos="1512"
 endpos="1528"
>
	<type  start="1473" length="20" line="21" chordsig="java.util.Collection"/>
	<type  start="1494" length="16" line="21" chordsig="java.lang.Thread"/>
	<newexpr line="21" chordsig="&lt;init&gt;:(Ljava/lang/String;)V@java.lang.RuntimeException" start="1543" length="16" type="invoke">
			<expr><![CDATA[new RuntimeException("Stub!")]]></expr>
		<param  start="1539" length="29" line="21">
			<expr><![CDATA[new RuntimeException("Stub!")]]></expr>
		</param>
		<param  start="1560" length="7" line="21">
			<expr><![CDATA["Stub!"]]></expr>
		</param>
	</newexpr>
	<type  start="1543" length="16" line="21" chordsig="java.lang.RuntimeException"/>
</method>
<method
 chordsig="hasWaiters:(Ljava/util/concurrent/locks/Condition;)Z@java.util.concurrent.locks.ReentrantLock"
 sig="boolean hasWaiters(Condition)"
 line="22"
 startpos="1588"
 endpos="1598"
>
	<marker line="-1" type="param">
		<operand  start="1636" length="9" line="22">
			<expr><![CDATA[condition]]></expr>
		</operand>
	</marker>
	<type  start="1599" length="36" line="22" chordsig="java.util.concurrent.locks.Condition"/>
	<newexpr line="22" chordsig="&lt;init&gt;:(Ljava/lang/String;)V@java.lang.RuntimeException" start="1659" length="16" type="invoke">
			<expr><![CDATA[new RuntimeException("Stub!")]]></expr>
		<param  start="1655" length="29" line="22">
			<expr><![CDATA[new RuntimeException("Stub!")]]></expr>
		</param>
		<param  start="1676" length="7" line="22">
			<expr><![CDATA["Stub!"]]></expr>
		</param>
	</newexpr>
	<type  start="1659" length="16" line="22" chordsig="java.lang.RuntimeException"/>
</method>
<method
 chordsig="getWaitQueueLength:(Ljava/util/concurrent/locks/Condition;)I@java.util.concurrent.locks.ReentrantLock"
 sig="int getWaitQueueLength(Condition)"
 line="23"
 startpos="1700"
 endpos="1718"
>
	<marker line="-1" type="param">
		<operand  start="1756" length="9" line="23">
			<expr><![CDATA[condition]]></expr>
		</operand>
	</marker>
	<type  start="1719" length="36" line="23" chordsig="java.util.concurrent.locks.Condition"/>
	<newexpr line="23" chordsig="&lt;init&gt;:(Ljava/lang/String;)V@java.lang.RuntimeException" start="1779" length="16" type="invoke">
			<expr><![CDATA[new RuntimeException("Stub!")]]></expr>
		<param  start="1775" length="29" line="23">
			<expr><![CDATA[new RuntimeException("Stub!")]]></expr>
		</param>
		<param  start="1796" length="7" line="23">
			<expr><![CDATA["Stub!"]]></expr>
		</param>
	</newexpr>
	<type  start="1779" length="16" line="23" chordsig="java.lang.RuntimeException"/>
</method>
<method
 chordsig="getWaitingThreads:(Ljava/util/concurrent/locks/Condition;)Ljava/util/Collection;@java.util.concurrent.locks.ReentrantLock"
 sig="Collection&lt;Thread&gt; getWaitingThreads(Condition)"
 line="24"
 startpos="1858"
 endpos="1875"
>
	<marker line="-1" type="param">
		<operand  start="1913" length="9" line="24">
			<expr><![CDATA[condition]]></expr>
		</operand>
	</marker>
	<type  start="1819" length="20" line="24" chordsig="java.util.Collection"/>
	<type  start="1840" length="16" line="24" chordsig="java.lang.Thread"/>
	<type  start="1876" length="36" line="24" chordsig="java.util.concurrent.locks.Condition"/>
	<newexpr line="24" chordsig="&lt;init&gt;:(Ljava/lang/String;)V@java.lang.RuntimeException" start="1936" length="16" type="invoke">
			<expr><![CDATA[new RuntimeException("Stub!")]]></expr>
		<param  start="1932" length="29" line="24">
			<expr><![CDATA[new RuntimeException("Stub!")]]></expr>
		</param>
		<param  start="1953" length="7" line="24">
			<expr><![CDATA["Stub!"]]></expr>
		</param>
	</newexpr>
	<type  start="1936" length="16" line="24" chordsig="java.lang.RuntimeException"/>
</method>
<method
 chordsig="toString:()Ljava/lang/String;@java.util.concurrent.locks.ReentrantLock"
 sig="String toString()"
 line="25"
 startpos="1990"
 endpos="1998"
>
	<type  start="1973" length="16" line="25" chordsig="java.lang.String"/>
	<newexpr line="25" chordsig="&lt;init&gt;:(Ljava/lang/String;)V@java.lang.RuntimeException" start="2013" length="16" type="invoke">
			<expr><![CDATA[new RuntimeException("Stub!")]]></expr>
		<param  start="2009" length="29" line="25">
			<expr><![CDATA[new RuntimeException("Stub!")]]></expr>
		</param>
		<param  start="2030" length="7" line="25">
			<expr><![CDATA["Stub!"]]></expr>
		</param>
	</newexpr>
	<type  start="2013" length="16" line="25" chordsig="java.lang.RuntimeException"/>
</method>
</class>
</root>
