<root>
<class chordsig="java.net.NetworkInterface" line="2">
<method
 chordsig="&lt;init&gt;:()V@java.net.NetworkInterface"
 sig="NetworkInterface()"
 line="4"
 startpos="56"
 endpos="72"
>
	<newexpr line="4" chordsig="&lt;init&gt;:(Ljava/lang/String;)V@java.lang.RuntimeException" start="87" length="16" type="invoke">
			<expr><![CDATA[new RuntimeException("Stub!")]]></expr>
		<param  start="83" length="29" line="4">
			<expr><![CDATA[new RuntimeException("Stub!")]]></expr>
		</param>
		<param  start="104" length="7" line="4">
			<expr><![CDATA["Stub!"]]></expr>
		</param>
	</newexpr>
	<type  start="87" length="16" line="4" chordsig="java.lang.RuntimeException"/>
</method>
<method
 chordsig="getName:()Ljava/lang/String;@java.net.NetworkInterface"
 sig="String getName()"
 line="5"
 startpos="141"
 endpos="148"
>
	<type  start="124" length="16" line="5" chordsig="java.lang.String"/>
	<newexpr line="5" chordsig="&lt;init&gt;:(Ljava/lang/String;)V@java.lang.RuntimeException" start="163" length="16" type="invoke">
			<expr><![CDATA[new RuntimeException("Stub!")]]></expr>
		<param  start="159" length="29" line="5">
			<expr><![CDATA[new RuntimeException("Stub!")]]></expr>
		</param>
		<param  start="180" length="7" line="5">
			<expr><![CDATA["Stub!"]]></expr>
		</param>
	</newexpr>
	<type  start="163" length="16" line="5" chordsig="java.lang.RuntimeException"/>
</method>
<method
 chordsig="getInetAddresses:()Ljava/util/Enumeration;@java.net.NetworkInterface"
 sig="Enumeration&lt;InetAddress&gt; getInetAddresses()"
 line="6"
 startpos="244"
 endpos="260"
>
	<type  start="200" length="21" line="6" chordsig="java.util.Enumeration"/>
	<type  start="222" length="20" line="6" chordsig="java.net.InetAddress"/>
	<newexpr line="6" chordsig="&lt;init&gt;:(Ljava/lang/String;)V@java.lang.RuntimeException" start="275" length="16" type="invoke">
			<expr><![CDATA[new RuntimeException("Stub!")]]></expr>
		<param  start="271" length="29" line="6">
			<expr><![CDATA[new RuntimeException("Stub!")]]></expr>
		</param>
		<param  start="292" length="7" line="6">
			<expr><![CDATA["Stub!"]]></expr>
		</param>
	</newexpr>
	<type  start="275" length="16" line="6" chordsig="java.lang.RuntimeException"/>
</method>
<method
 chordsig="getDisplayName:()Ljava/lang/String;@java.net.NetworkInterface"
 sig="String getDisplayName()"
 line="7"
 startpos="329"
 endpos="343"
>
	<type  start="312" length="16" line="7" chordsig="java.lang.String"/>
	<newexpr line="7" chordsig="&lt;init&gt;:(Ljava/lang/String;)V@java.lang.RuntimeException" start="358" length="16" type="invoke">
			<expr><![CDATA[new RuntimeException("Stub!")]]></expr>
		<param  start="354" length="29" line="7">
			<expr><![CDATA[new RuntimeException("Stub!")]]></expr>
		</param>
		<param  start="375" length="7" line="7">
			<expr><![CDATA["Stub!"]]></expr>
		</param>
	</newexpr>
	<type  start="358" length="16" line="7" chordsig="java.lang.RuntimeException"/>
</method>
<method
 chordsig="getByName:(Ljava/lang/String;)Ljava/net/NetworkInterface;@java.net.NetworkInterface"
 sig="NetworkInterface getByName(String)"
 line="8"
 startpos="428"
 endpos="437"
>
	<marker line="-1" type="param">
		<operand  start="455" length="13" line="8">
			<expr><![CDATA[interfaceName]]></expr>
		</operand>
	</marker>
	<type  start="402" length="25" line="8" chordsig="java.net.NetworkInterface"/>
	<type  start="438" length="16" line="8" chordsig="java.lang.String"/>
	<newexpr line="8" chordsig="&lt;init&gt;:(Ljava/lang/String;)V@java.lang.RuntimeException" start="514" length="16" type="invoke">
			<expr><![CDATA[new RuntimeException("Stub!")]]></expr>
		<param  start="510" length="29" line="8">
			<expr><![CDATA[new RuntimeException("Stub!")]]></expr>
		</param>
		<param  start="531" length="7" line="8">
			<expr><![CDATA["Stub!"]]></expr>
		</param>
	</newexpr>
	<type  start="514" length="16" line="8" chordsig="java.lang.RuntimeException"/>
</method>
<method
 chordsig="getByInetAddress:(Ljava/net/InetAddress;)Ljava/net/NetworkInterface;@java.net.NetworkInterface"
 sig="NetworkInterface getByInetAddress(InetAddress)"
 line="9"
 startpos="584"
 endpos="600"
>
	<marker line="-1" type="param">
		<operand  start="622" length="7" line="9">
			<expr><![CDATA[address]]></expr>
		</operand>
	</marker>
	<type  start="558" length="25" line="9" chordsig="java.net.NetworkInterface"/>
	<type  start="601" length="20" line="9" chordsig="java.net.InetAddress"/>
	<newexpr line="9" chordsig="&lt;init&gt;:(Ljava/lang/String;)V@java.lang.RuntimeException" start="675" length="16" type="invoke">
			<expr><![CDATA[new RuntimeException("Stub!")]]></expr>
		<param  start="671" length="29" line="9">
			<expr><![CDATA[new RuntimeException("Stub!")]]></expr>
		</param>
		<param  start="692" length="7" line="9">
			<expr><![CDATA["Stub!"]]></expr>
		</param>
	</newexpr>
	<type  start="675" length="16" line="9" chordsig="java.lang.RuntimeException"/>
</method>
<method
 chordsig="getNetworkInterfaces:()Ljava/util/Enumeration;@java.net.NetworkInterface"
 sig="Enumeration&lt;NetworkInterface&gt; getNetworkInterfaces()"
 line="10"
 startpos="768"
 endpos="788"
>
	<type  start="719" length="21" line="10" chordsig="java.util.Enumeration"/>
	<type  start="741" length="25" line="10" chordsig="java.net.NetworkInterface"/>
	<newexpr line="10" chordsig="&lt;init&gt;:(Ljava/lang/String;)V@java.lang.RuntimeException" start="835" length="16" type="invoke">
			<expr><![CDATA[new RuntimeException("Stub!")]]></expr>
		<param  start="831" length="29" line="10">
			<expr><![CDATA[new RuntimeException("Stub!")]]></expr>
		</param>
		<param  start="852" length="7" line="10">
			<expr><![CDATA["Stub!"]]></expr>
		</param>
	</newexpr>
	<type  start="835" length="16" line="10" chordsig="java.lang.RuntimeException"/>
</method>
<method
 chordsig="equals:(Ljava/lang/Object;)Z@java.net.NetworkInterface"
 sig="boolean equals(Object)"
 line="11"
 startpos="880"
 endpos="886"
>
	<marker line="-1" type="param">
		<operand  start="904" length="3" line="11">
			<expr><![CDATA[obj]]></expr>
		</operand>
	</marker>
	<type  start="887" length="16" line="11" chordsig="java.lang.Object"/>
	<newexpr line="11" chordsig="&lt;init&gt;:(Ljava/lang/String;)V@java.lang.RuntimeException" start="921" length="16" type="invoke">
			<expr><![CDATA[new RuntimeException("Stub!")]]></expr>
		<param  start="917" length="29" line="11">
			<expr><![CDATA[new RuntimeException("Stub!")]]></expr>
		</param>
		<param  start="938" length="7" line="11">
			<expr><![CDATA["Stub!"]]></expr>
		</param>
	</newexpr>
	<type  start="921" length="16" line="11" chordsig="java.lang.RuntimeException"/>
</method>
<method
 chordsig="hashCode:()I@java.net.NetworkInterface"
 sig="int hashCode()"
 line="12"
 startpos="962"
 endpos="970"
>
	<newexpr line="12" chordsig="&lt;init&gt;:(Ljava/lang/String;)V@java.lang.RuntimeException" start="985" length="16" type="invoke">
			<expr><![CDATA[new RuntimeException("Stub!")]]></expr>
		<param  start="981" length="29" line="12">
			<expr><![CDATA[new RuntimeException("Stub!")]]></expr>
		</param>
		<param  start="1002" length="7" line="12">
			<expr><![CDATA["Stub!"]]></expr>
		</param>
	</newexpr>
	<type  start="985" length="16" line="12" chordsig="java.lang.RuntimeException"/>
</method>
<method
 chordsig="toString:()Ljava/lang/String;@java.net.NetworkInterface"
 sig="String toString()"
 line="13"
 startpos="1039"
 endpos="1047"
>
	<type  start="1022" length="16" line="13" chordsig="java.lang.String"/>
	<newexpr line="13" chordsig="&lt;init&gt;:(Ljava/lang/String;)V@java.lang.RuntimeException" start="1062" length="16" type="invoke">
			<expr><![CDATA[new RuntimeException("Stub!")]]></expr>
		<param  start="1058" length="29" line="13">
			<expr><![CDATA[new RuntimeException("Stub!")]]></expr>
		</param>
		<param  start="1079" length="7" line="13">
			<expr><![CDATA["Stub!"]]></expr>
		</param>
	</newexpr>
	<type  start="1062" length="16" line="13" chordsig="java.lang.RuntimeException"/>
</method>
<method
 chordsig="getInterfaceAddresses:()Ljava/util/List;@java.net.NetworkInterface"
 sig="List&lt;InterfaceAddress&gt; getInterfaceAddresses()"
 line="14"
 startpos="1141"
 endpos="1162"
>
	<type  start="1099" length="14" line="14" chordsig="java.util.List"/>
	<type  start="1114" length="25" line="14" chordsig="java.net.InterfaceAddress"/>
	<newexpr line="14" chordsig="&lt;init&gt;:(Ljava/lang/String;)V@java.lang.RuntimeException" start="1177" length="16" type="invoke">
			<expr><![CDATA[new RuntimeException("Stub!")]]></expr>
		<param  start="1173" length="29" line="14">
			<expr><![CDATA[new RuntimeException("Stub!")]]></expr>
		</param>
		<param  start="1194" length="7" line="14">
			<expr><![CDATA["Stub!"]]></expr>
		</param>
	</newexpr>
	<type  start="1177" length="16" line="14" chordsig="java.lang.RuntimeException"/>
</method>
<method
 chordsig="getSubInterfaces:()Ljava/util/Enumeration;@java.net.NetworkInterface"
 sig="Enumeration&lt;NetworkInterface&gt; getSubInterfaces()"
 line="15"
 startpos="1263"
 endpos="1279"
>
	<type  start="1214" length="21" line="15" chordsig="java.util.Enumeration"/>
	<type  start="1236" length="25" line="15" chordsig="java.net.NetworkInterface"/>
	<newexpr line="15" chordsig="&lt;init&gt;:(Ljava/lang/String;)V@java.lang.RuntimeException" start="1294" length="16" type="invoke">
			<expr><![CDATA[new RuntimeException("Stub!")]]></expr>
		<param  start="1290" length="29" line="15">
			<expr><![CDATA[new RuntimeException("Stub!")]]></expr>
		</param>
		<param  start="1311" length="7" line="15">
			<expr><![CDATA["Stub!"]]></expr>
		</param>
	</newexpr>
	<type  start="1294" length="16" line="15" chordsig="java.lang.RuntimeException"/>
</method>
<method
 chordsig="getParent:()Ljava/net/NetworkInterface;@java.net.NetworkInterface"
 sig="NetworkInterface getParent()"
 line="16"
 startpos="1357"
 endpos="1366"
>
	<type  start="1331" length="25" line="16" chordsig="java.net.NetworkInterface"/>
	<newexpr line="16" chordsig="&lt;init&gt;:(Ljava/lang/String;)V@java.lang.RuntimeException" start="1381" length="16" type="invoke">
			<expr><![CDATA[new RuntimeException("Stub!")]]></expr>
		<param  start="1377" length="29" line="16">
			<expr><![CDATA[new RuntimeException("Stub!")]]></expr>
		</param>
		<param  start="1398" length="7" line="16">
			<expr><![CDATA["Stub!"]]></expr>
		</param>
	</newexpr>
	<type  start="1381" length="16" line="16" chordsig="java.lang.RuntimeException"/>
</method>
<method
 chordsig="isUp:()Z@java.net.NetworkInterface"
 sig="boolean isUp()"
 line="17"
 startpos="1426"
 endpos="1430"
>
	<newexpr line="17" chordsig="&lt;init&gt;:(Ljava/lang/String;)V@java.lang.RuntimeException" start="1477" length="16" type="invoke">
			<expr><![CDATA[new RuntimeException("Stub!")]]></expr>
		<param  start="1473" length="29" line="17">
			<expr><![CDATA[new RuntimeException("Stub!")]]></expr>
		</param>
		<param  start="1494" length="7" line="17">
			<expr><![CDATA["Stub!"]]></expr>
		</param>
	</newexpr>
	<type  start="1477" length="16" line="17" chordsig="java.lang.RuntimeException"/>
</method>
<method
 chordsig="isLoopback:()Z@java.net.NetworkInterface"
 sig="boolean isLoopback()"
 line="18"
 startpos="1522"
 endpos="1532"
>
	<newexpr line="18" chordsig="&lt;init&gt;:(Ljava/lang/String;)V@java.lang.RuntimeException" start="1579" length="16" type="invoke">
			<expr><![CDATA[new RuntimeException("Stub!")]]></expr>
		<param  start="1575" length="29" line="18">
			<expr><![CDATA[new RuntimeException("Stub!")]]></expr>
		</param>
		<param  start="1596" length="7" line="18">
			<expr><![CDATA["Stub!"]]></expr>
		</param>
	</newexpr>
	<type  start="1579" length="16" line="18" chordsig="java.lang.RuntimeException"/>
</method>
<method
 chordsig="isPointToPoint:()Z@java.net.NetworkInterface"
 sig="boolean isPointToPoint()"
 line="19"
 startpos="1624"
 endpos="1638"
>
	<newexpr line="19" chordsig="&lt;init&gt;:(Ljava/lang/String;)V@java.lang.RuntimeException" start="1685" length="16" type="invoke">
			<expr><![CDATA[new RuntimeException("Stub!")]]></expr>
		<param  start="1681" length="29" line="19">
			<expr><![CDATA[new RuntimeException("Stub!")]]></expr>
		</param>
		<param  start="1702" length="7" line="19">
			<expr><![CDATA["Stub!"]]></expr>
		</param>
	</newexpr>
	<type  start="1685" length="16" line="19" chordsig="java.lang.RuntimeException"/>
</method>
<method
 chordsig="supportsMulticast:()Z@java.net.NetworkInterface"
 sig="boolean supportsMulticast()"
 line="20"
 startpos="1730"
 endpos="1747"
>
	<newexpr line="20" chordsig="&lt;init&gt;:(Ljava/lang/String;)V@java.lang.RuntimeException" start="1794" length="16" type="invoke">
			<expr><![CDATA[new RuntimeException("Stub!")]]></expr>
		<param  start="1790" length="29" line="20">
			<expr><![CDATA[new RuntimeException("Stub!")]]></expr>
		</param>
		<param  start="1811" length="7" line="20">
			<expr><![CDATA["Stub!"]]></expr>
		</param>
	</newexpr>
	<type  start="1794" length="16" line="20" chordsig="java.lang.RuntimeException"/>
</method>
<method
 chordsig="getHardwareAddress:()[B@java.net.NetworkInterface"
 sig="byte[] getHardwareAddress()"
 line="21"
 startpos="1838"
 endpos="1856"
>
	<newexpr line="21" chordsig="&lt;init&gt;:(Ljava/lang/String;)V@java.lang.RuntimeException" start="1903" length="16" type="invoke">
			<expr><![CDATA[new RuntimeException("Stub!")]]></expr>
		<param  start="1899" length="29" line="21">
			<expr><![CDATA[new RuntimeException("Stub!")]]></expr>
		</param>
		<param  start="1920" length="7" line="21">
			<expr><![CDATA["Stub!"]]></expr>
		</param>
	</newexpr>
	<type  start="1903" length="16" line="21" chordsig="java.lang.RuntimeException"/>
</method>
<method
 chordsig="getMTU:()I@java.net.NetworkInterface"
 sig="int getMTU()"
 line="22"
 startpos="1944"
 endpos="1950"
>
	<newexpr line="22" chordsig="&lt;init&gt;:(Ljava/lang/String;)V@java.lang.RuntimeException" start="1997" length="16" type="invoke">
			<expr><![CDATA[new RuntimeException("Stub!")]]></expr>
		<param  start="1993" length="29" line="22">
			<expr><![CDATA[new RuntimeException("Stub!")]]></expr>
		</param>
		<param  start="2014" length="7" line="22">
			<expr><![CDATA["Stub!"]]></expr>
		</param>
	</newexpr>
	<type  start="1997" length="16" line="22" chordsig="java.lang.RuntimeException"/>
</method>
<method
 chordsig="isVirtual:()Z@java.net.NetworkInterface"
 sig="boolean isVirtual()"
 line="23"
 startpos="2042"
 endpos="2051"
>
	<newexpr line="23" chordsig="&lt;init&gt;:(Ljava/lang/String;)V@java.lang.RuntimeException" start="2066" length="16" type="invoke">
			<expr><![CDATA[new RuntimeException("Stub!")]]></expr>
		<param  start="2062" length="29" line="23">
			<expr><![CDATA[new RuntimeException("Stub!")]]></expr>
		</param>
		<param  start="2083" length="7" line="23">
			<expr><![CDATA["Stub!"]]></expr>
		</param>
	</newexpr>
	<type  start="2066" length="16" line="23" chordsig="java.lang.RuntimeException"/>
</method>
</class>
</root>
